tolisp/__init__.py
tolisp/main.py
tolisp-0.1.0.dist-info/licenses/LICENSE
tolisp-0.1.0.dist-info/METADATA
tolisp-0.1.0.dist-info/WHEEL
tolisp-0.1.0.dist-info/entry_points.txt
tolisp-0.1.0.dist-info/top_level.txt
tolisp-0.1.0.dist-info/RECORD
