Metadata-Version: 2.4
Name: tolisp
Version: 0.1.0
Summary: Convert YAML/JSON files to Lisp style S-expressions
Home-page: https://github.com/riAssinstAr
Author: Ankit Kumar Ravi
License: MIT
Classifier: Programming Language :: Python :: 3
Classifier: License :: OSI Approved :: MIT License
Requires-Python: >=3.7
License-File: LICENSE
Requires-Dist: pyyaml
Dynamic: author
Dynamic: classifier
Dynamic: description
Dynamic: description-content-type
Dynamic: home-page
Dynamic: license
Dynamic: license-file
Dynamic: requires-dist
Dynamic: requires-python
Dynamic: summary
